{
    "Name": "",
    "TimeLayouts": {},
    "ClassPlans": {
        "e0a97eee-ffff-4c64-9bff-37fb3abe9829": {
            "TimeLayoutId": "16d829c5-5884-4688-8a8a-91d555ea8706",
            "TimeRule": {
                "WeekDay": 1,
                "WeekCountDiv": 0,
                "IsActive": false
            },
            "Classes": [
                {
                    "SubjectId": "3bbed0c0-bcf3-4dfe-a78d-5da9b02cf8bd",
                    "IsActive": false
                },
                {
                    "SubjectId": "3bbed0c0-bcf3-4dfe-a78d-5da9b02cf8bd",
                    "IsActive": false
                },
                {
                    "SubjectId": "97d0bf3f-137f-4f8a-87d6-ff387063bbd3",
                    "IsActive": false
                },
                {
                    "SubjectId": "1154d452-5ede-4194-b4dd-cb40c956c8ed",
                    "IsActive": false
                },
                {
                    "SubjectId": "97d0bf3f-137f-4f8a-87d6-ff387063bbd3",
                    "IsActive": false
                },
                {
                    "SubjectId": "9f0d71b7-b4da-4040-a3d5-64da7573c6dd",
                    "IsActive": false
                },
                {
                    "SubjectId": "d18e9906-0210-4f00-9dd6-b919f0dd8287",
                    "IsActive": false
                },
                {
                    "SubjectId": "d173b427-d269-42f3-b6a3-adb175d9cc7a",
                    "IsActive": false
                },
                {
                    "SubjectId": "d173b427-d269-42f3-b6a3-adb175d9cc7a",
                    "IsActive": false
                },
                {
                    "SubjectId": "ad55fbe6-295a-45e6-b0ce-68ec287b8338",
                    "IsActive": false
                },
                {
                    "SubjectId": "d18e9906-0210-4f00-9dd6-b919f0dd8287",
                    "IsActive": false
                },
                {
                    "SubjectId": "a4a76e77-29d8-4103-882c-2f4c9d1e8077",
                    "IsActive": false
                }
            ],
            "Name": "\u661F\u671F\u4E00",
            "IsOverlay": false,
            "OverlaySourceId": null,
            "OverlaySetupTime": "2024-08-31T23:47:35.7527388+08:00",
            "IsEnabled": true,
            "AttachedObjects": {},
            "IsActive": false
        },
        "ae27ed3b-7f01-4a7e-bad3-37bce36c1c00": {
            "TimeLayoutId": "16d829c5-5884-4688-8a8a-91d555ea8706",
            "TimeRule": {
                "WeekDay": 2,
                "WeekCountDiv": 0,
                "IsActive": false
            },
            "Classes": [
                {
                    "SubjectId": "97d0bf3f-137f-4f8a-87d6-ff387063bbd3",
                    "IsActive": false
                },
                {
                    "SubjectId": "3bbed0c0-bcf3-4dfe-a78d-5da9b02cf8bd",
                    "IsActive": false
                },
                {
                    "SubjectId": "97d0bf3f-137f-4f8a-87d6-ff387063bbd3",
                    "IsActive": false
                },
                {
                    "SubjectId": "1154d452-5ede-4194-b4dd-cb40c956c8ed",
                    "IsActive": false
                },
                {
                    "SubjectId": "1154d452-5ede-4194-b4dd-cb40c956c8ed",
                    "IsActive": false
                },
                {
                    "SubjectId": "a4a76e77-29d8-4103-882c-2f4c9d1e8077",
                    "IsActive": false
                },
                {
                    "SubjectId": "0ed2307b-4d9b-48fa-97ed-94bd2213c84e",
                    "IsActive": false
                },
                {
                    "SubjectId": "44ec22d3-3dde-40e6-8eb7-a1f4cd378a04",
                    "IsActive": false
                },
                {
                    "SubjectId": "44ec22d3-3dde-40e6-8eb7-a1f4cd378a04",
                    "IsActive": false
                },
                {
                    "SubjectId": "ad55fbe6-295a-45e6-b0ce-68ec287b8338",
                    "IsActive": false
                },
                {
                    "SubjectId": "1154d452-5ede-4194-b4dd-cb40c956c8ed",
                    "IsActive": false
                },
                {
                    "SubjectId": "44ec22d3-3dde-40e6-8eb7-a1f4cd378a04",
                    "IsActive": false
                }
            ],
            "Name": "\u661F\u671F\u4E8C",
            "IsOverlay": false,
            "OverlaySourceId": null,
            "OverlaySetupTime": "2024-08-31T23:48:15.4750234+08:00",
            "IsEnabled": true,
            "AttachedObjects": {},
            "IsActive": false
        },
        "138e3ab7-11e6-4ddc-923e-62f0aeb9fccd": {
            "TimeLayoutId": "16d829c5-5884-4688-8a8a-91d555ea8706",
            "TimeRule": {
                "WeekDay": 3,
                "WeekCountDiv": 1,
                "IsActive": false
            },
            "Classes": [
                {
                    "SubjectId": "3bbed0c0-bcf3-4dfe-a78d-5da9b02cf8bd",
                    "IsActive": false
                },
                {
                    "SubjectId": "3bbed0c0-bcf3-4dfe-a78d-5da9b02cf8bd",
                    "IsActive": false
                },
                {
                    "SubjectId": "a4a76e77-29d8-4103-882c-2f4c9d1e8077",
                    "IsActive": false
                },
                {
                    "SubjectId": "1154d452-5ede-4194-b4dd-cb40c956c8ed",
                    "IsActive": false
                },
                {
                    "SubjectId": "3bbed0c0-bcf3-4dfe-a78d-5da9b02cf8bd",
                    "IsActive": false
                },
                {
                    "SubjectId": "a4a76e77-29d8-4103-882c-2f4c9d1e8077",
                    "IsActive": false
                },
                {
                    "SubjectId": "97d0bf3f-137f-4f8a-87d6-ff387063bbd3",
                    "IsActive": false
                },
                {
                    "SubjectId": "d18e9906-0210-4f00-9dd6-b919f0dd8287",
                    "IsActive": false
                },
                {
                    "SubjectId": "a4a76e77-29d8-4103-882c-2f4c9d1e8077",
                    "IsActive": false
                },
                {
                    "SubjectId": "ad55fbe6-295a-45e6-b0ce-68ec287b8338",
                    "IsActive": false
                },
                {
                    "SubjectId": "97d0bf3f-137f-4f8a-87d6-ff387063bbd3",
                    "IsActive": false
                },
                {
                    "SubjectId": "3bbed0c0-bcf3-4dfe-a78d-5da9b02cf8bd",
                    "IsActive": false
                }
            ],
            "Name": "\u661F\u671F\u4E09",
            "IsOverlay": false,
            "OverlaySourceId": null,
            "OverlaySetupTime": "2024-08-31T23:48:37.243297+08:00",
            "IsEnabled": true,
            "AttachedObjects": {},
            "IsActive": false
        },
        "b2c9d278-7cc9-4664-9b24-ad57e5008925": {
            "TimeLayoutId": "16d829c5-5884-4688-8a8a-91d555ea8706",
            "TimeRule": {
                "WeekDay": 3,
                "WeekCountDiv": 2,
                "IsActive": false
            },
            "Classes": [
                {
                    "SubjectId": "3bbed0c0-bcf3-4dfe-a78d-5da9b02cf8bd",
                    "IsActive": false
                },
                {
                    "SubjectId": "3bbed0c0-bcf3-4dfe-a78d-5da9b02cf8bd",
                    "IsActive": false
                },
                {
                    "SubjectId": "d18e9906-0210-4f00-9dd6-b919f0dd8287",
                    "IsActive": false
                },
                {
                    "SubjectId": "1154d452-5ede-4194-b4dd-cb40c956c8ed",
                    "IsActive": false
                },
                {
                    "SubjectId": "3bbed0c0-bcf3-4dfe-a78d-5da9b02cf8bd",
                    "IsActive": false
                },
                {
                    "SubjectId": "a4a76e77-29d8-4103-882c-2f4c9d1e8077",
                    "IsActive": false
                },
                {
                    "SubjectId": "97d0bf3f-137f-4f8a-87d6-ff387063bbd3",
                    "IsActive": false
                },
                {
                    "SubjectId": "d18e9906-0210-4f00-9dd6-b919f0dd8287",
                    "IsActive": false
                },
                {
                    "SubjectId": "a4a76e77-29d8-4103-882c-2f4c9d1e8077",
                    "IsActive": false
                },
                {
                    "SubjectId": "ad55fbe6-295a-45e6-b0ce-68ec287b8338",
                    "IsActive": false
                },
                {
                    "SubjectId": "97d0bf3f-137f-4f8a-87d6-ff387063bbd3",
                    "IsActive": false
                },
                {
                    "SubjectId": "3bbed0c0-bcf3-4dfe-a78d-5da9b02cf8bd",
                    "IsActive": false
                }
            ],
            "Name": "\u661F\u671F\u4E092",
            "IsOverlay": false,
            "OverlaySourceId": null,
            "OverlaySetupTime": "2024-08-31T23:49:03.812568+08:00",
            "IsEnabled": true,
            "AttachedObjects": {},
            "IsActive": false
        },
        "d2c6d1d9-36a1-4b1b-a2a2-21b535c65c58": {
            "TimeLayoutId": "16d829c5-5884-4688-8a8a-91d555ea8706",
            "TimeRule": {
                "WeekDay": 4,
                "WeekCountDiv": 0,
                "IsActive": false
            },
            "Classes": [
                {
                    "SubjectId": "97d0bf3f-137f-4f8a-87d6-ff387063bbd3",
                    "IsActive": false
                },
                {
                    "SubjectId": "1154d452-5ede-4194-b4dd-cb40c956c8ed",
                    "IsActive": false
                },
                {
                    "SubjectId": "d18e9906-0210-4f00-9dd6-b919f0dd8287",
                    "IsActive": false
                },
                {
                    "SubjectId": "3bbed0c0-bcf3-4dfe-a78d-5da9b02cf8bd",
                    "IsActive": false
                },
                {
                    "SubjectId": "0ed2307b-4d9b-48fa-97ed-94bd2213c84e",
                    "IsActive": false
                },
                {
                    "SubjectId": "ea1520f4-77d2-46fc-9892-8d61c8e5ce3a",
                    "IsActive": false
                },
                {
                    "SubjectId": "ea1520f4-77d2-46fc-9892-8d61c8e5ce3a",
                    "IsActive": false
                },
                {
                    "SubjectId": "3719a855-0ad8-467b-aba3-108816bd4e51",
                    "IsActive": false
                },
                {
                    "SubjectId": "d18e9906-0210-4f00-9dd6-b919f0dd8287",
                    "IsActive": false
                },
                {
                    "SubjectId": "ad55fbe6-295a-45e6-b0ce-68ec287b8338",
                    "IsActive": false
                },
                {
                    "SubjectId": "9f0d71b7-b4da-4040-a3d5-64da7573c6dd",
                    "IsActive": false
                },
                {
                    "SubjectId": "3bbed0c0-bcf3-4dfe-a78d-5da9b02cf8bd",
                    "IsActive": false
                }
            ],
            "Name": "\u661F\u671F\u56DB",
            "IsOverlay": false,
            "OverlaySourceId": null,
            "OverlaySetupTime": "2024-08-31T23:49:19.20279+08:00",
            "IsEnabled": true,
            "AttachedObjects": {},
            "IsActive": false
        },
        "9541920b-e415-4661-ac26-0c30f035e487": {
            "TimeLayoutId": "16d829c5-5884-4688-8a8a-91d555ea8706",
            "TimeRule": {
                "WeekDay": 5,
                "WeekCountDiv": 0,
                "IsActive": false
            },
            "Classes": [
                {
                    "SubjectId": "1154d452-5ede-4194-b4dd-cb40c956c8ed",
                    "IsActive": false
                },
                {
                    "SubjectId": "1154d452-5ede-4194-b4dd-cb40c956c8ed",
                    "IsActive": false
                },
                {
                    "SubjectId": "3bbed0c0-bcf3-4dfe-a78d-5da9b02cf8bd",
                    "IsActive": false
                },
                {
                    "SubjectId": "9f0d71b7-b4da-4040-a3d5-64da7573c6dd",
                    "IsActive": false
                },
                {
                    "SubjectId": "9f0d71b7-b4da-4040-a3d5-64da7573c6dd",
                    "IsActive": false
                },
                {
                    "SubjectId": "a4a76e77-29d8-4103-882c-2f4c9d1e8077",
                    "IsActive": false
                },
                {
                    "SubjectId": "44ec22d3-3dde-40e6-8eb7-a1f4cd378a04",
                    "IsActive": false
                },
                {
                    "SubjectId": "95dd61cd-5d2e-4f23-80e8-99be8aa97028",
                    "IsActive": false
                },
                {
                    "SubjectId": "95dd61cd-5d2e-4f23-80e8-99be8aa97028",
                    "IsActive": false
                },
                {
                    "SubjectId": "ad55fbe6-295a-45e6-b0ce-68ec287b8338",
                    "IsActive": false
                },
                {
                    "SubjectId": "1154d452-5ede-4194-b4dd-cb40c956c8ed",
                    "IsActive": false
                },
                {
                    "SubjectId": "97d0bf3f-137f-4f8a-87d6-ff387063bbd3",
                    "IsActive": false
                }
            ],
            "Name": "\u661F\u671F\u4E94",
            "IsOverlay": false,
            "OverlaySourceId": null,
            "OverlaySetupTime": "2024-08-31T23:50:15.2285634+08:00",
            "IsEnabled": true,
            "AttachedObjects": {},
            "IsActive": false
        },
        "44cf3393-36ef-4769-a60d-611ea70a5285": {
            "TimeLayoutId": "16d829c5-5884-4688-8a8a-91d555ea8706",
            "TimeRule": {
                "WeekDay": 6,
                "WeekCountDiv": 0,
                "IsActive": false
            },
            "Classes": [
                {
                    "SubjectId": "97d0bf3f-137f-4f8a-87d6-ff387063bbd3",
                    "IsActive": false
                },
                {
                    "SubjectId": "97d0bf3f-137f-4f8a-87d6-ff387063bbd3",
                    "IsActive": false
                },
                {
                    "SubjectId": "97d0bf3f-137f-4f8a-87d6-ff387063bbd3",
                    "IsActive": false
                },
                {
                    "SubjectId": "1154d452-5ede-4194-b4dd-cb40c956c8ed",
                    "IsActive": false
                },
                {
                    "SubjectId": "1154d452-5ede-4194-b4dd-cb40c956c8ed",
                    "IsActive": false
                },
                {
                    "SubjectId": "a4a76e77-29d8-4103-882c-2f4c9d1e8077",
                    "IsActive": false
                },
                {
                    "SubjectId": "d18e9906-0210-4f00-9dd6-b919f0dd8287",
                    "IsActive": false
                },
                {
                    "SubjectId": "97d0bf3f-137f-4f8a-87d6-ff387063bbd3",
                    "IsActive": false
                },
                {
                    "SubjectId": "97d0bf3f-137f-4f8a-87d6-ff387063bbd3",
                    "IsActive": false
                },
                {
                    "SubjectId": "ad55fbe6-295a-45e6-b0ce-68ec287b8338",
                    "IsActive": false
                },
                {
                    "SubjectId": "1154d452-5ede-4194-b4dd-cb40c956c8ed",
                    "IsActive": false
                },
                {
                    "SubjectId": "d18e9906-0210-4f00-9dd6-b919f0dd8287",
                    "IsActive": false
                }
            ],
            "Name": "\u661F\u671F\u516D",
            "IsOverlay": false,
            "OverlaySourceId": null,
            "OverlaySetupTime": "2024-08-31T23:50:33.3705829+08:00",
            "IsEnabled": true,
            "AttachedObjects": {
                "58e5b69a-764a-472b-bcf7-003b6a8c7fdf": {
                    "IsAttachSettingsEnabled": false,
                    "ShowExtraInfoOnTimePoint": true,
                    "ExtraInfoType": 0,
                    "IsCountdownEnabled": true,
                    "CountdownSeconds": 60,
                    "IsActive": false
                },
                "08f0d9c3-c770-4093-a3d0-02f3d90c24bc": {
                    "IsClassOnNotificationEnabled": true,
                    "IsClassOnPreparingNotificationEnabled": true,
                    "IsClassOffNotificationEnabled": true,
                    "ClassPreparingDeltaTime": 60,
                    "ClassOnPreparingText": "\u51C6\u5907\u4E0A\u8BFE\uFF0C\u8BF7\u56DE\u5230\u5EA7\u4F4D\u5E76\u4FDD\u6301\u5B89\u9759\uFF0C\u505A\u597D\u4E0A\u8BFE\u51C6\u5907\u3002",
                    "IsAttachSettingsEnabled": false,
                    "IsActive": false
                },
                "8fbc3a26-6d20-44dd-b895-b9411e3ddc51": {
                    "IsEnabled": true,
                    "NotificationMsg": "\u4ECA\u5929\u7684\u8BFE\u7A0B\u5DF2\u7ED3\u675F\uFF0C\u8BF7\u540C\u5B66\u4EEC\u6709\u5E8F\u79BB\u5F00\u3002",
                    "IsAttachSettingsEnabled": false,
                    "IsActive": false
                }
            },
            "IsActive": false
        },
        "3f55b8fa-8a91-4d76-b0d0-bee6c0d6ade5": {
            "TimeLayoutId": "16d829c5-5884-4688-8a8a-91d555ea8706",
            "TimeRule": {
                "WeekDay": 0,
                "WeekCountDiv": 0,
                "IsActive": false
            },
            "Classes": [
                {
                    "SubjectId": "3bbed0c0-bcf3-4dfe-a78d-5da9b02cf8bd",
                    "IsActive": false
                },
                {
                    "SubjectId": "1154d452-5ede-4194-b4dd-cb40c956c8ed",
                    "IsActive": false
                },
                {
                    "SubjectId": "1154d452-5ede-4194-b4dd-cb40c956c8ed",
                    "IsActive": false
                },
                {
                    "SubjectId": "3bbed0c0-bcf3-4dfe-a78d-5da9b02cf8bd",
                    "IsActive": false
                },
                {
                    "SubjectId": "3bbed0c0-bcf3-4dfe-a78d-5da9b02cf8bd",
                    "IsActive": false
                },
                {
                    "SubjectId": "3bbed0c0-bcf3-4dfe-a78d-5da9b02cf8bd",
                    "IsActive": false
                },
                {
                    "SubjectId": "3bbed0c0-bcf3-4dfe-a78d-5da9b02cf8bd",
                    "IsActive": false
                },
                {
                    "SubjectId": "44ec22d3-3dde-40e6-8eb7-a1f4cd378a04",
                    "IsActive": false
                },
                {
                    "SubjectId": "9f0d71b7-b4da-4040-a3d5-64da7573c6dd",
                    "IsActive": false
                },
                {
                    "SubjectId": "ad55fbe6-295a-45e6-b0ce-68ec287b8338",
                    "IsActive": false
                },
                {
                    "SubjectId": "97d0bf3f-137f-4f8a-87d6-ff387063bbd3",
                    "IsActive": false
                },
                {
                    "SubjectId": "3bbed0c0-bcf3-4dfe-a78d-5da9b02cf8bd",
                    "IsActive": false
                }
            ],
            "Name": "\u661F\u671F\u65E5",
            "IsOverlay": false,
            "OverlaySourceId": null,
            "OverlaySetupTime": "2024-08-31T23:50:50.7309494+08:00",
            "IsEnabled": true,
            "AttachedObjects": {},
            "IsActive": false
        }
    },
    "Subjects": {},
    "IsOverlayClassPlanEnabled": false,
    "OverlayClassPlanId": null,
    "TempClassPlanId": null,
    "TempClassPlanSetupTime": "2024-08-30T00:03:47.983713+08:00",
    "IsActive": false
}